aes/__init__.py
aes/aes.py
aes-1.0.1.dist-info/LICENSE
aes-1.0.1.dist-info/METADATA
aes-1.0.1.dist-info/WHEEL
aes-1.0.1.dist-info/top_level.txt
aes-1.0.1.dist-info/RECORD
