Metadata-Version: 2.1
Name: aes
Version: 1.0.1
Summary: AES(Advanced Encryption Standard) in Python
Home-page: https://github.com/DonggeunKwon/aes
Author: Donggeun Kwon
Author-email: donggeun.kwon@gmail.com
License: MIT
Keywords: AES,Cipher,Advanced Encryption Standard
Classifier: Programming Language :: Python :: 3
Classifier: Operating System :: OS Independent
Classifier: License :: OSI Approved :: MIT License
Classifier: Development Status :: 2 - Pre-Alpha
Requires-Python: >=3
License-File: LICENSE
